mleap/__init__.py
mleap/version.py
mleap/bundle/__init__.py
mleap/bundle/serialize.py
mleap/gensim/__init__.py
mleap/gensim/word2vec.py
mleap/pyspark/__init__.py
mleap/pyspark/py2scala.py
mleap/pyspark/spark_support.py
mleap/pyspark/feature/__init__.py
mleap/pyspark/feature/math_binary.py
mleap/pyspark/feature/math_unary.py
mleap/pyspark/feature/string_map.py
mleap/sklearn/__init__.py
mleap/sklearn/base.py
mleap/sklearn/feature_union.py
mleap/sklearn/logistic.py
mleap/sklearn/pipeline.py
mleap/sklearn/svm.py
mleap/sklearn/decomposition/__init__.py
mleap/sklearn/decomposition/pca.py
mleap/sklearn/ensemble/__init__.py
mleap/sklearn/ensemble/forest.py
mleap/sklearn/extensions/__init__.py
mleap/sklearn/extensions/data.py
mleap/sklearn/feature_extraction/__init__.py
mleap/sklearn/feature_extraction/text.py
mleap/sklearn/preprocessing/__init__.py
mleap/sklearn/preprocessing/data.py
mleap/sklearn/tree/__init__.py
mleap/sklearn/tree/tree.py
mleap/tensorflow/__init__.py
mleap/tensorflow/test.py
tests/__init__.py
tests/gensim_test.py
tests/pyspark/__init__.py
tests/pyspark/feature/__init__.py
tests/pyspark/feature/math_binary_test.py
tests/pyspark/feature/math_unary_test.py
tests/pyspark/feature/string_map_test.py
tests/pyspark/lib/__init__.py
tests/pyspark/lib/assertions.py
tests/pyspark/lib/spark_session.py
tests/sklearn/__init__.py
tests/sklearn/base_tests.py
tests/sklearn/extensions/__init__.py
tests/sklearn/extensions/data_test.py
tests/sklearn/extensions/imputer_extension_test.py
tests/sklearn/feature_extraction/__init__.py
tests/sklearn/feature_extraction/text_test.py
tests/sklearn/preprocessing/__init__.py
tests/sklearn/preprocessing/data_test.py
tests/sklearn/preprocessing/imputer_test.py
tests/sklearn/preprocessing/one_hot_encoder_test.py
tests/sklearn/tree/__init__.py
tests/sklearn/tree/tree_test.py
mleap-0.23.3.dist-info/AUTHORS.md
mleap-0.23.3.dist-info/METADATA
mleap-0.23.3.dist-info/WHEEL
mleap-0.23.3.dist-info/top_level.txt
mleap-0.23.3.dist-info/RECORD
